[
  {
    "first_name": "Shane",
    "last_name": "Harris",
    "email": "Stella5@yahoo.com"
  },
  {
    "first_name": "Maximus",
    "last_name": "Larkin",
    "email": "Terrence63@gmail.com"
  },
  {
    "first_name": "Vito",
    "last_name": "Harris",
    "email": "Donnell_Emmerich@yahoo.com"
  },
  {
    "first_name": "Vena",
    "last_name": "Ritchie",
    "email": "Ethel_Blanda@gmail.com"
  },
  {
    "first_name": "Jeanie",
    "last_name": "Kutch",
    "email": "Keely.Feil83@yahoo.com"
  },
  {
    "first_name": "Flossie",
    "last_name": "Roberts",
    "email": "Terence_Welch@yahoo.com"
  },
  {
    "first_name": "Victoria",
    "last_name": "Hilpert",
    "email": "Margot_Kuhic84@gmail.com"
  },
  {
    "first_name": "Urban",
    "last_name": "Bauch",
    "email": "Mozelle43@yahoo.com"
  },
  {
    "first_name": "Dora",
    "last_name": "Pagac",
    "email": "Diamond.Sipes96@gmail.com"
  },
  {
    "first_name": "Stacey",
    "last_name": "Hoeger",
    "email": "Jacklyn_Swift@gmail.com"
  }
]